{
  "title": "Tune In to the Midnight Heart (Mayonaka Heart Tune)",
  "description": "\"Late at night, alone on my bed, your voice was the only thing that saved me. I want to talk to you again. There's something I want to say.\"\n\nWithout knowing her real name or face, Yamabuki Arisu, a second-year high school student, was looking for a girl named \"Apollo'' who was a livestreamer. However, one day, Arisu gets a clue about Apollo from the broadcast club of the high school where she is going. There were 4 beautiful girls who dreamed of \"getting a job related to voice\"!! Who is Apollo? What will happen to the dreams of the four people? A cute yet hard-working success romantic comedy begins here!!\n\n",
  "artist": "Masakuni Igarashi",
  "author": "Masakuni Igarashi",
  "cover": "https://imgur.com/xi6egct",
  "chapters": {
    "1": {
      "title": "Mayonaka Heart Tune - Chapter 1: Re:start",
      "volume": "1",
      "last_updated": "1715438643",
      "groups": {
        "": "https://cubari.moe/read/imgur/vwpLf0D/1/1/"
      }
    },
    "2": {
      "title": "Mayonaka Heart Tune - Chapter 2: A Message From Arisu Yamabuki",
      "volume": "1",
      "last_updated": "1715440497",
      "groups": {
        "": "https://cubari.moe/read/imgur/9UKT2G7/1/1/"
      }
    },
    "3": {
      "title": "Mayonaka Heart Tune - Chapter 3: Liar",
      "volume": "1",
      "last_updated": "1715440588",
      "groups": {
        "": "https://cubari.moe/read/imgur/GwHwWkQ/1/1/"
      }
    },
    "4": {
      "title": "Mayonaka Heart Tune Chapter 4 - Three Weeks Until The Kiss",
      "volume": "1",
      "last_updated": "1715440687",
      "groups": {
        "": "https://cubari.moe/read/imgur/ZU5sZ6I/1/1/"
      }
    },
    "5": {
      "title": "Mayonaka Heart Tune Chapter 5 - Overture",
      "volume": "1",
      "last_updated": "1715440733",
      "groups": {
        "": "https://cubari.moe/read/imgur/iEMU2h8/1/1/"
      }
    },
    "6": {
      "title": "Mayonaka Heart Tune Chapter 6 - Lock the door if it's embarrassing",
      "volume": "1",
      "last_updated": "1715440769",
      "groups": {
        "": "https://cubari.moe/read/imgur/qzMYxAT/1/1/"
      }
    },
    "7": {
      "title": "Mayonaka Heart Tune Chapter 7 - I can't smile in front of the camera!",
      "volume": "1",
      "last_updated": "1715440808",
      "groups": {
        "": "https://cubari.moe/read/imgur/In6F4lb/1/1/"
      }
    },
    "8": {
      "title": "Mayonaka Heart Tune Chapter 8 - I Can't Smile In Front Of You!",
      "volume": "1",
      "last_updated": "1715440830",
      "groups": {
        "": "https://cubari.moe/read/imgur/GyDloqd/1/1/"
      }
    },
    "9": {
      "title": "Mayonaka Heart Tune Chapter 9 - All alone with you until dark",
      "volume": "1",
      "last_updated": "1715440919",
      "groups": {
        "": "https://cubari.moe/read/imgur/zO987KA/1/1/"
      }
    },
    "10": {
      "title": "Mayonaka Heart Tune Chapter 10 - Partners in Crime",
      "volume": "1",
      "last_updated": "1715441053",
      "groups": {
        "": "https://cubari.moe/read/imgur/ZaJeeZX/1/1/"
      }
    },
    "11": {
      "title": "Mayonaka Heart Tune Chapter 11 - The adviser's name is literally Lemon-chan",
      "volume": "1",
      "last_updated": "1715441297",
      "groups": {
        "": "https://cubari.moe/read/imgur/MKdYJpq/1/1/"
      }
    },
    "12": {
      "title": "Mayonaka Heart Tune Chapter 12 - I can't tell whose voice it was",
      "volume": "1",
      "last_updated": "1715441318",
      "groups": {
        "": "https://cubari.moe/read/imgur/O1ha3HG/1/1/"
      }
    },
    "13": {
      "title": "Mayonaka Heart Tune Chapter 13: Arisu Yamabuki-kun",
      "volume": "1",
      "last_updated": "1715441349",
      "groups": {
        "": "https://cubari.moe/read/imgur/pBMR1FI/1/1/"
      }
    },
    "14": {
      "title": "Mayonaka Heart Tune Chapter 14: Flyby Anomaly",
      "volume": "1",
      "last_updated": "1715441385",
      "groups": {
        "": "https://cubari.moe/read/imgur/lO5EWEw/1/1/"
      }
    },
    "15": {
      "title": "Mayonaka Heart Tune Chapter 15: Nene Saw",
      "volume": "1",
      "last_updated": "1715441406",
      "groups": {
        "": "https://cubari.moe/read/imgur/Odj73W4/1/1/"
      }
    },
    "16": {
      "title": "Mayonaka Heart Tune Chapter 16: Piece of cake",
      "volume": "1",
      "last_updated": "1715441458",
      "groups": {
        "": "https://cubari.moe/read/imgur/y24nbRn/1/1/"
      }
    },
    "17": {
      "title": "Mayonaka Heart Tune Chapter 17: \"This is very hot, so please be careful\"",
      "volume": "1",
      "last_updated": "1715441485",
      "groups": {
        "": "https://cubari.moe/read/imgur/QFdPILW/1/1/"
      }
    },
    "18": {
      "title": "Mayonaka Heart Tune Chapter 18 - \"20 points is still within the margin of error\"",
      "volume": "1",
      "last_updated": "1715441504",
      "groups": {
        "": "https://cubari.moe/read/imgur/dgzn8dQ/1/1/"
      }
    },
    "19": {
      "title": "Mayonaka Heart Tune Chapter 19 - Forgetful",
      "volume": "1",
      "last_updated": "1715441542",
      "groups": {
        "": "https://cubari.moe/read/imgur/XiRLJN9/1/1/"
      }
    },
    "20": {
      "title": "Mayonaka Heart Tune Chapter 20: \"Emotion is a spontaneous process\"",
      "volume": "1",
      "last_updated": "1715441592",
      "groups": {
        "": "https://cubari.moe/read/imgur/DtcjbxX/1/1/"
      }
    },
    "21": {
      "title": "Mayonaka Heart Tune Chapter 21: Affection is an escalating process",
      "volume": "1",
      "last_updated": "1715441722",
      "groups": {
        "": "https://cubari.moe/read/imgur/37E1i5T/1/1/"
      }
    },
    "22": {
      "title": "Mayonaka Heart Tune Chapter 22: Payback achieved",
      "volume": "1",
      "last_updated": "1715441746",
      "groups": {
        "": "https://cubari.moe/read/imgur/EfHJZ5r/1/1/"
      }
    },
    "23": {
      "title": "Mayonaka Heart Tune Chapter 23: This is all your fault",
      "volume": "1",
      "last_updated": "1715441785",
      "groups": {
        "": "https://cubari.moe/read/imgur/1fWlWys/1/1/"
      }
    },
    "24": {
      "title": "Mayonaka Heart Tune Chapter 24 - A bolt from the blue",
      "volume": "1",
      "last_updated": "1715441822",
      "groups": {
        "": "https://cubari.moe/read/imgur/vavu8tE/1/1/"
      }
    },
    "25": {
      "title": "Mayonaka Heart Tune Chapter 25: \"Direct Contact\"",
      "volume": "1",
      "last_updated": "1715441836",
      "groups": {
        "": "https://cubari.moe/read/imgur/r00eQ9R/1/1/"
      }
    },
    "26": {
      "title": "Mayonaka Heart Tune Chapter 26: Black wind, white rain",
      "volume": "1",
      "last_updated": "1715441858",
      "groups": {
        "": "https://cubari.moe/read/imgur/fU543iA/1/1/"
      }
    },
    "27": {
      "title": "Mayonaka Heart Tune Chapter 27 - Kiss or hug",
      "volume": "1",
      "last_updated": "1715441878",
      "groups": {
        "": "https://cubari.moe/read/imgur/MYiCDX9/1/1/"
      }
    },
    "28": {
      "title": "Mayonaka Heart Tune Chapter 28: While one wasn't looking",
      "volume": "1",
      "last_updated": "1715441900",
      "groups": {
        "": "https://cubari.moe/read/imgur/oP7GWnj/1/1/"
      }
    },
    "29": {
      "title": "Tune in to the Midnight Heart (Mayonaka Heart Tune) - Chapter 29",
      "volume": "1",
      "last_updated": "1715441946",
      "groups": {
        "": "https://cubari.moe/read/imgur/0RmljmQ/1/1/"
      }
    }
  }
}